odoo/addons/ssi_partner_hr_profile/README.rst
odoo/addons/ssi_partner_hr_profile/__init__.py
odoo/addons/ssi_partner_hr_profile/__manifest__.py
odoo/addons/ssi_partner_hr_profile/static/description/icon.png
odoo/addons/ssi_partner_hr_profile/views/hr_employee_views.xml
odoo/addons/ssi_partner_hr_profile/views/res_users_views.xml
odoo14_addon_ssi_partner_hr_profile-14.0.1.0.1.dev1.dist-info/METADATA
odoo14_addon_ssi_partner_hr_profile-14.0.1.0.1.dev1.dist-info/WHEEL
odoo14_addon_ssi_partner_hr_profile-14.0.1.0.1.dev1.dist-info/top_level.txt
odoo14_addon_ssi_partner_hr_profile-14.0.1.0.1.dev1.dist-info/RECORD
